trunk/twoFF4phase/def.v
`define DATA_WIDTHS  8 // Need to be adjusted
`define DATAS  8'b1010_1111 // Need to be adjusted

/*parameter aw = `address_width-1; // RB :see def.v ...
parameter dw = `data_width-1;
parameter sw = `select_width-1;
parameter data_address = 8'b1111_1111;*/

trunk/twoFF4phase/dff.v
module dff(/*AUTOARG*/
   // Outputs
   q,
   // Inputs
   d, clk, reset
   );

   input d,clk,reset;
   output q;
   /*AUTOREG*/
   // Beginning of automatic regs (for this module's undeclared outputs)
   reg			q;
   // End of automatics

   /*AUTOWIRE*/
   always @(posedge clk or posedge reset) begin
      if(reset) begin
	 q <= 1'b0; //using non blocking assignments for the sequential logic
      end else begin
	q <= d;
      end
   end

endmodule // DFF

trunk/twoFF4phase/rxfsm.v
module receiver(/*AUTOARG*/
   // Outputs
   output_rx, ack, d,
   // Inputs
   clk, reset, req, input_rx
   );
`include "def.v"

        parameter  DATA_WIDTH = `DATA_WIDTHS,
           DATA_MSB = DATA_WIDTH-1,
           DATA = `DATAS;

   input                clk, reset, req;   
   input [DATA_MSB:0]   input_rx; //Data input from other core
   output [DATA_MSB:0]  output_rx; //Data received
   output               ack, d;

   /*AUTOREG*/
   // Beginning of automatic regs (for this module's undeclared outputs)
   reg			ack;
   reg			d;
   reg [DATA_MSB:0]	output_rx;
   // End of automatics

   reg 			r3;   
   wire 		r1, r2;
   reg statemachine;
     
   parameter  rst = 2'b00;  // Asynchronous reset state
   parameter  idle = 2'b01;  // Wait for the input 'v'
   parameter  acknowledge = 2'b10; // Data is on the bus, send the request to receiver (this is push synchronizer)
   parameter  waiting = 2'b11; // Waiting for the deassertion of ack
   
   reg[1:0]  current_state, next_state;
   /* Instantiate the two(can be extended depending on MTBF requirment) flip flops for the req input- this avoids metastability till MTBF*/
   dff  dff1(.q(r1), .d(req), .clk(clk), .reset(reset));
   dff  dff2(.q(r2), .d(r1), .clk(clk), .reset(reset));
   
   always @(posedge clk or posedge reset) begin
      r3 <= r2;
      d <= (!r3) & r2;
      if(reset) begin
	 output_rx <= 0;
         statemachine <= 1'b0;	 
      end else begin
	 if(r2 == 1'b1) begin
	    output_rx <= input_rx; /* Latch the data into Rx-buffer*/	  
	    statemachine <= 1'b1;    
	 end 
      end
   end 
   
    always@(posedge clk or posedge reset) begin
      
       if(reset) begin
	  current_state <= rst;
       end else begin
	  current_state <= next_state;
       end
    end
   
   always @(*) begin
      next_state = current_state;
      if(statemachine) begin        
      case(current_state)
	 rst: begin
	    next_state = idle;
	    ack = 1'b0;
	 end

	 idle: begin
	    if(r2 == 1'b1) begin 
	       next_state = acknowledge;
	       ack = 1'b1;	       
	    end
	 end

	  acknowledge: begin
	    if(r2 == 1'b0) begin
	       next_state = idle;
	       ack = 1'b0;	       
	    end	    
	 end

	 default: begin
	    next_state = idle;
	    ack = 1'b0;	    
	 end	
      endcase // case (current_state)
      end
   end // always @ (*)

endmodule // receiver

trunk/twoFF4phase/txfsm.v
module transmitter(/*AUTOARG*/
   // Outputs
   output_tx, req, f,
   // Inputs
   clk, v, reset, ack, input_tx
   );
`include "def.v"

   parameter  DATA_WIDTH = `DATA_WIDTHS,
           DATA_MSB = DATA_WIDTH-1,
           DATA = `DATAS;

   input                clk,v,reset,ack;
   input [DATA_MSB:0]   input_tx; // Plug-in the data that has to be transmitted to other core
   output [DATA_MSB:0]  output_tx; // Tx-buffer
   output               req,f;

   /*AUTOREG*/
   // Beginning of automatic regs (for this module's undeclared outputs)
   reg			f;
   reg [DATA_MSB:0]	output_tx;
   reg			req;
   // End of automatics

   reg 	     a3;   
   wire      a1, a2;

   parameter  rst = 2'b00;  // Asynchronous reset state
   parameter  idle = 2'b01;  // Wait for the input 'v'
   parameter  request = 2'b10; // Data is on the bus, send the request to receiver (this is push synchronizer)
   parameter  waiting = 2'b11; // Waiting for the deassertion of ack
   
   reg[1:0]  current_state, next_state;   
   reg statemachine;

   /* Instantiate the two(can be extended depending on MTBF requirment) flip flops for the ack input- this avoids metastability till MTBF */
   dff  dff1(.q(a1), .d(ack), .clk(clk), .reset(reset));
   dff  dff2(.q(a2), .d(a1), .clk(clk), .reset(reset));
   
   always @(posedge clk or posedge reset) begin
      a3 <= a2;
      f <= (! a3) & a2;
      if(reset) begin
	 output_tx <= 0;
         statemachine <= 1'b0;	 
      end else begin
	 if (v == 1'b1) begin
	    output_tx <= input_tx; // Put the data into transmit data buffer	   
	    statemachine <= 1'b1;
	 end	 
      end
   end   

   
/*This task handles the transmitter state machine*/
     
    always @(posedge clk) begin        
       if(reset) begin
	  current_state <= rst;
       end else begin
	  current_state <= next_state;
       end
    end
   
   always @(*) begin
      next_state = current_state;
      if(statemachine) begin
      case(current_state) 
	 rst: begin
	    next_state = idle;
	    req = 1'b0;
	 end

	 idle: begin
	    if(v == 1'b1) begin 
	       next_state = request;
	       req = 1'b1;	       
	    end
	 end

	 request: begin
	    if(a2 == 1'b1) begin
	       next_state = waiting;
	       req = 1'b0;	       
	    end	    
	 end

	 waiting: begin
	    if(a2 == 1'b0) begin
	       next_state = idle;
	    end   
	 end
	
	 default: begin
	    next_state = idle;
	    req = 1'b0;	    
	 end	
      endcase // case (current_state)
      end  
   end // always @ (*)


endmodule // transmitter

trunk/twoFF4phase/sync.v
module sync_multi(/*AUTOARG*/
   // Outputs
   out_data, f, d,
   // Inputs
   in_data, v, clk, reset
   );

`include "def.v"

   parameter  DATA_WIDTH = `DATA_WIDTHS,
     DATA_MSB = DATA_WIDTH-1,
     DATA = `DATAS;

   output [DATA_MSB:0] out_data;
   output 	       f, d;
   input [DATA_MSB:0]  in_data;
   input 	       v, clk, reset;

   /*AUTOREG*/
   // Beginning of automatic regs (for this module's undeclared outputs)
   reg			d;
   reg			f;
   wire [DATA_MSB:0]	out_data;
   // End of automatics
   wire [DATA_MSB:0]   data;   
   wire ack1, req1, f1, d1;
 
   transmitter tx1(.output_tx(data), .req(req1), .f(f1), .clk(clk), .v(v), .reset(reset), .ack(ack1), .input_tx(in_data));
   receiver rx1(.output_rx(out_data), .ack(ack1), .d(d1), .clk(clk), .reset(reset), .req(req1), .input_rx(data));
        always @* begin
                f =f1;
                d =d1;
        end           
endmodule // sync_multi

twoFF4phase/sync_tb.v
module sync_tb();
`include "def.v"

parameter  DATA_WIDTH = `DATA_WIDTHS,
           DATA_MSB = DATA_WIDTH-1,
           DATA = `DATAS;

   wire [DATA_MSB:0]  outs;
   wire f, d;
   reg [DATA_MSB:0] data_core;
   reg 		    clk, reset, v;
 
   sync_multi syncss1(.out_data(outs), .f(f), .d(d), .in_data(data_core), .v(v), .clk(clk), .reset(reset));
   
   initial        
     clk = 1'b0;
   always
     #1 clk = ~clk;

   initial
     begin
     $dumpvars;
	#1 reset = 1'b1;
	#1 data_core = DATA;
	#1 reset = 1'b0;
	
        #2 v = 1'b1;
        #10 v = 1'b0;
        #1 data_core = 8'b0011_0101;
        #1 v = 1'b1;
        #10 v = 1'b0;
        #100 $finish;
     end
   
endmodule // sync_tb

trunk/twoFF4phase/dump.vcd
$date
	Tue Feb 14 21:38:15 2012
$end
$version
	Icarus Verilog
$end
$timescale
	1s
$end
$scope module sync_tb $end
$var wire 1 ! d $end
$var wire 1 " f $end
$var wire 8 # outs [7:0] $end
$var reg 1 $ clk $end
$var reg 8 % data_core [7:0] $end
$var reg 1 & reset $end
$var reg 1 ' v $end
$scope module syncss1 $end
$var wire 1 ( ack1 $end
$var wire 1 ) clk $end
$var wire 1 * d1 $end
$var wire 8 + data [7:0] $end
$var wire 1 , f1 $end
$var wire 8 - in_data [7:0] $end
$var wire 8 . out_data [7:0] $end
$var wire 1 / req1 $end
$var wire 1 0 reset $end
$var wire 1 1 v $end
$var reg 1 2 d $end
$var reg 1 3 f $end
$scope module tx1 $end
$var wire 1 4 a1 $end
$var wire 1 5 a2 $end
$var wire 1 ( ack $end
$var wire 1 ) clk $end
$var wire 8 6 input_tx [7:0] $end
$var wire 1 0 reset $end
$var wire 1 1 v $end
$var reg 1 7 a3 $end
$var reg 2 8 current_state [1:0] $end
$var reg 1 9 f $end
$var reg 2 : next_state [1:0] $end
$var reg 8 ; output_tx [7:0] $end
$var reg 1 < req $end
$var reg 1 = statemachine $end
$scope module dff1 $end
$var wire 1 ) clk $end
$var wire 1 ( d $end
$var wire 1 0 reset $end
$var reg 1 > q $end
$upscope $end
$scope module dff2 $end
$var wire 1 ) clk $end
$var wire 1 4 d $end
$var wire 1 0 reset $end
$var reg 1 ? q $end
$upscope $end
$upscope $end
$scope module rx1 $end
$var wire 1 ) clk $end
$var wire 8 @ input_rx [7:0] $end
$var wire 1 A r1 $end
$var wire 1 B r2 $end
$var wire 1 / req $end
$var wire 1 0 reset $end
$var reg 1 C ack $end
$var reg 2 D current_state [1:0] $end
$var reg 1 E d $end
$var reg 2 F next_state [1:0] $end
$var reg 8 G output_rx [7:0] $end
$var reg 1 H r3 $end
$var reg 1 I statemachine $end
$scope module dff1 $end
$var wire 1 ) clk $end
$var wire 1 / d $end
$var wire 1 0 reset $end
$var reg 1 J q $end
$upscope $end
$scope module dff2 $end
$var wire 1 ) clk $end
$var wire 1 A d $end
$var wire 1 0 reset $end
$var reg 1 K q $end
$upscope $end
$upscope $end
$upscope $end
$upscope $end
$enddefinitions $end
#0
$dumpvars
xK
xJ
xI
xH
bx G
bx F
xE
bx D
xC
xB
xA
bx @
x?
x>
x=
x<
bx ;
bx :
x9
bx 8
x7
bx 6
x5
x4
x3
x2
x1
x0
x/
bx .
bx -
x,
bx +
x*
0)
x(
x'
x&
bx %
0$
bx #
x"
x!
$end
#1
b0 :
b0 F
0>
04
0?
05
0=
b0 ;
b0 +
b0 @
0J
0A
0K
0B
0I
b0 G
b0 #
b0 .
b0 8
b0 D
1&
10
1$
1)
#2
b10101111 %
b10101111 -
b10101111 6
0$
0)
#3
xJ
xA
x>
x4
0&
00
1$
1)
#4
0$
0)
#5
0<
0/
b1 :
03
0"
x?
x5
1=
b10101111 ;
b10101111 +
b10101111 @
09
0,
07
xK
xB
1$
1)
1'
11
#6
0$
0)
#7
x3
x"
1<
1/
b10 :
0J
0A
x9
x,
x7
b1 8
1$
1)
#8
0$
0)
#9
1J
1A
0K
0B
b10 8
1$
1)
#10
0$
0)
#11
1K
1B
1$
1)
#12
0$
0)
#13
0C
0(
b1 F
1I
1H
b10101111 G
b10101111 #
b10101111 .
1$
1)
#14
0$
0)
#15
02
0!
1C
1(
b10 F
0E
0*
0>
04
b1 D
1$
1)
0'
01
#16
0$
0)
b110101 %
b110101 -
b110101 6
#17
1>
14
0?
05
b110101 ;
b110101 +
b110101 @
b10 D
1$
1)
1'
11
#18
0$
0)
#19
03
0"
0<
0/
b11 :
b110101 G
b110101 #
b110101 .
09
0,
07
1?
15
1$
1)
#20
0$
0)
#21
13
1"
19
1,
17
0J
0A
b11 8
1$
1)
#22
0$
0)
#23
0C
0(
b1 F
03
0"
0K
0B
09
0,
1$
1)
#24
0$
0)
#25
0>
04
b1 D
1$
1)
#26
0$
0)
#27
b1 :
0?
05
1$
1)
0'
01
#28
0$
0)
#29
b1 8
1$
1)
