trunk/twoFF_4phase_slow_highlevel/def.v
parameter  DATA_WIDTH = 8,
  DATA_MSB = DATA_WIDTH-1,
  DATA = 8'b1010_1111;

trunk/twoFF_4phase_slow_highlevel/txrx.v
`include "timescale.v"
module tx (/*AUTOARG*/
	   // Outputs
	   snt, req, data,
	   // Inputs
	   vi, ack, clk, reset, sdata
	   );
`include "def.v"
   output snt, req;
   output [DATA_MSB:0] data;
   input 	       vi, ack, clk, reset;
   input [DATA_MSB:0]  sdata;
   
   /*AUTOREG*/
   // Beginning of automatic regs (for this module's undeclared outputs)
   reg [DATA_MSB:0]    data;
   wire 	       req;
   wire 	       snt;
   // End of automatics
   
   reg 		       a2, a1, a2d;
   wire 	       vi, txe;
   
   txfsmslow txfsm(.txe(txe), .req(req), .vi(vi), .a2(a2), .clk(clk), .reset(reset));
   
   always @(posedge clk or posedge reset) begin
      if(reset) begin
	 data <=  {(1+(DATA_MSB)){1'b0}};
	 a1 <= 1'b0;
	 a2 <= 1'b0;
	 a2d <= 1'b0;
      end else begin
	 if(txe) begin
	    data <= sdata;
	 end
	 a1 <= ack;
	 a2 <= a1;
	 a2d <= a2;	
      end     
   end // always @ (posedge clk or posedge reset)
   
   assign snt = a2 & (~a2d);  
   
endmodule // tx

module rx (/*AUTOARG*/
	   // Outputs
	   ack, vo, rdata,
	   // Inputs
	   req, clk, reset, data
	   );
`include "def.v"
   
   output ack, vo;
   output [DATA_MSB:0] rdata;
   input 	       req, clk, reset;   
   input [DATA_MSB:0]  data;
   
   /*AUTOREG*/
   // Beginning of automatic regs (for this module's undeclared outputs)
   reg 		       ack;
   reg [DATA_MSB:0]    rdata;
   reg 		       vo;
   // End of automatics
   //wire [DATA_MSB:0]	rdata;
   reg 		       r1, r2, r2d;
   
   always @(posedge clk or posedge reset) begin
      if(reset) begin
	 rdata <=  {(1+(DATA_MSB)){1'b0}};
	 r1 <= 1'b0;
	 r2 <= 1'b0;
	 r2d <= 1'b0;
	 ack <= 1'b0;
	 vo <= 1'b0;	 
      end else begin
	 if(rxe) begin
	    rdata <= data;	    
	 end
	 r1 <= req;
	 r2 <= r1;
	 r2d <= r2;	
	 ack <= r2;
	 vo <= rxe;	 
      end
   end // rx
   
   /*always @* begin
    rdata = rdata1;
   end*/
   assign rxe = r2 & (~r2d);     
endmodule // rx

twoFF_slow/txfsmslow.v
module txfsmslow(/*AUTOARG*/
   // Outputs
   txe, req,
   // Inputs
   vi, clk, a2, reset
   );
`include "def.v"

   output txe, req;
   input  vi, clk, a2, reset;
   
   parameter  rst = 2'b00;  // Asynchronous reset state
   parameter  wdata = 2'b01;  // Wait for the input 'v'
   parameter  wack = 2'b10; // Data is on the bus, send the request to receiver (this is push synchronizer)
   //parameter  waiting = 2'b11; // Waiting for the deassertion of ack

   /*AUTOREG*/
   // Beginning of automatic regs (for this module's undeclared outputs)
   reg			req;
   reg			txe;
   // End of automatics
   reg [1:0] 		current_state, next_state;   
   
   /*This task handles the transmitter state machine*/
   
    always @(posedge clk or posedge reset) begin        
       if(reset) begin
	  current_state <= rst;
       end else begin
	  current_state <= next_state;
       end
    end
   
   always @(*) begin
      next_state = current_state;
	 case(current_state) 
	   rst: begin
	      txe = 1'b0;
	      req = 1'b0;	      
	      next_state = wdata;	    
	   end
	   
	   wdata: begin
	      req = 1'b0;
	      txe = 1'b1;	      
	      if(vi == 1'b1 && a2 == 1'b0) begin 		      
		 next_state = wack;
	      end else if (vi == 1'b0 || a2 == 1'b1) begin
		  next_state = wdata;
	      end
	   end
	   
	   wack: begin
	      req = 1'b1;
	      txe = 1'b1;
	      if(a2 == 1'b1) begin		    
		 next_state = wdata;   
	      end else if (a2 == 1'b0) begin
		 next_state = wack;		 
	      end	    
	   end
	   
	   default: begin	 
	      req = 1'b0;
	      txe = 1'b0;
	      next_state = wdata;	    
	   end	
	 endcase // case (current_state)        
   end // always @ (*)

endmodule // txfsm_slow

wb_and_bridge/twoFF_4phase_bridge/bridge_top.v
module bridge_top(/*AUTOARG*/
   // Outputs
   rdata_m, rdata_s, snt_m, vo_m, snt_s, vo_s,
   // Inputs
   sdata_m, sdata_s, vi_m, vi_s, clk_m, clk_s, rst_m, rst_s
   );
`include "def.v"
   output [DATA_MSB:0] rdata_m, rdata_s;
   output 	       snt_m, vo_m, snt_s, vo_s;
   input [DATA_MSB:0]  sdata_m, sdata_s;
   input 	       vi_m, vi_s;
   input 	       clk_m, clk_s;
   input 	       rst_m, rst_s;
   
   
 
   // Beginning of automatic regs (for this module's undeclared outputs)
   wire [DATA_MSB:0]	rdata_m;
   wire [DATA_MSB:0]	rdata_s;
   wire			snt_m;
   wire			snt_s;
   wire			vo_m;
   wire			vo_s;
   // End of automatics

   /* Intermediate signals*/
   wire [DATA_MSB:0] 	data1, data2;
   wire 		snt1, req1;
   wire 		snt2, req2;
   

   /*Instanstiate to complete the bridge which has 2 tx and 2 rx*/
   tx tx_wbmaster(
		  // Outputs
		  .data			(data1[DATA_MSB:0]),
		  .snt			(snt_m),
		  .req			(req1),
		  // Inputs
		  .sdata		(sdata_m[DATA_MSB:0]),
		  .vi			(vi_m),
		  .ack			(ack1),
		  .clk			(clk_m),
		  .reset		(rst_m));
   
   rx rx_wbmaster(
		  // Outputs
		  .rdata		(rdata_m[DATA_MSB:0]),
		  .ack			(ack1),
		  .vo			(vo_s),
		  // Inputs
		  .data			(data1[DATA_MSB:0]),
		  .req			(req1),
		  .clk			(clk_s),
		  .reset		(rst_m));
   
   tx tx_wbslave(
		 // Outputs
		 .data			(data2[DATA_MSB:0]),
		 .snt			(snt_s),
		 .req			(req2),
		 // Inputs
		 .sdata			(sdata_s[DATA_MSB:0]),
		 .vi			(vi_s),
		 .ack			(ack2),
		 .clk			(clk_s),
		 .reset			(rst_s));
   
   rx rx_wbslave(
		 // Outputs
		 .rdata			(rdata_s[DATA_MSB:0]),
		 .ack			(ack2),
		 .vo			(vo_m),
		 // Inputs
		 .data			(data2[DATA_MSB:0]),
		 .req			(req2),
		 .clk			(clk_s),
		 .reset			(rst_s));
   
   
endmodule // bridge_top

trunk/wb_and_bridge/twoFF_4phase_bridge/bridge_tb.v
`include "timescale.v"
module bridge_tb();
`include "def.v"

   reg 		      clk_m, clk_s, rst_m, rst_s, vi_m, vi_s;
   reg [DATA_MSB:0]   sdata_m, sdata_s;
   
   wire [DATA_MSB:0]  rdata_m, rdata_s;
   wire 	      snt_m, snt_s, vo_m, vo_s;
   
   
   bridge_top bridge_top_U0(/*AUTOINST*/
			    // Outputs
			    .rdata_m		(rdata_m[DATA_MSB:0]),
			    .rdata_s		(rdata_s[DATA_MSB:0]),
			    .snt_m		(snt_m),
			    .vo_m		(vo_m),
			    .snt_s		(snt_s),
			    .vo_s		(vo_s),
			    // Inputs
			    .sdata_m		(sdata_m[DATA_MSB:0]),
			    .sdata_s		(sdata_s[DATA_MSB:0]),
			    .vi_m		(vi_m),
			    .vi_s		(vi_s),
			    .clk_m		(clk_m),
			    .clk_s		(clk_s),
			    .rst_m		(rst_m),
			    .rst_s		(rst_s));
   initial        
     clk_m = 1'b0;
   always
     #1 clk_m = ~clk_m; //m-clk
   
   initial        
     clk_s = 1'b0;
   always
     #1 clk_s = ~clk_s; //s-clk

   initial begin
      $dumpvars;
      vi_m = 1'b0;
      vi_s = 1'b0;
      rst_m = 1'b1;
      rst_s = 1'b1;

      #2 rst_m = 1'b0;
         rst_s = 1'b0;
      #1 sdata_m = 1'b1;
         sdata_s = 1'b1;
      #1 vi_m = 1'b1;
         vi_s = 1'b1;
      #2 vi_m = 1'b0;
         vi_s = 1'b0;
            #250 $finish;
      end

      
endmodule // bridge_tb

trunk/twoFF_4phase_slow_highlevel/dump.vcd
$date
	Wed Mar  7 09:32:20 2012
$end
$version
	Icarus Verilog
$end
$timescale
	10ps
$end
$scope module bridge_tb $end
$var wire 1 ! rdata_m $end
$var wire 1 " rdata_s $end
$var wire 1 # snt_m $end
$var wire 1 $ snt_s $end
$var wire 1 % vo_m $end
$var wire 1 & vo_s $end
$var reg 1 ' clk_m $end
$var reg 1 ( clk_s $end
$var reg 1 ) rst_m $end
$var reg 1 * rst_s $end
$var reg 1 + sdata_m $end
$var reg 1 , sdata_s $end
$var reg 1 - vi_m $end
$var reg 1 . vi_s $end
$scope module bridge_top_U0 $end
$var wire 1 / ack1 $end
$var wire 1 0 ack2 $end
$var wire 1 1 clk_m $end
$var wire 1 2 clk_s $end
$var wire 1 3 data1 $end
$var wire 1 4 data2 $end
$var wire 1 ! rdata_m $end
$var wire 1 " rdata_s $end
$var wire 1 5 req1 $end
$var wire 1 6 req2 $end
$var wire 1 7 rst_m $end
$var wire 1 8 rst_s $end
$var wire 1 9 sdata_m $end
$var wire 1 : sdata_s $end
$var wire 1 # snt_m $end
$var wire 1 $ snt_s $end
$var wire 1 ; vi_m $end
$var wire 1 < vi_s $end
$var wire 1 % vo_m $end
$var wire 1 & vo_s $end
$scope module tx_wbmaster $end
$var wire 1 / ack $end
$var wire 1 1 clk $end
$var wire 1 5 req $end
$var wire 1 7 reset $end
$var wire 1 9 sdata $end
$var wire 1 # snt $end
$var wire 1 = txe $end
$var wire 1 ; vi $end
$var reg 1 > a1 $end
$var reg 1 ? a2 $end
$var reg 1 @ a2d $end
$var reg 1 A data $end
$scope module txfsm $end
$var wire 1 B a2 $end
$var wire 1 1 clk $end
$var wire 1 7 reset $end
$var wire 1 ; vi $end
$var reg 2 C current_state [1:0] $end
$var reg 2 D next_state [1:0] $end
$var reg 1 E req $end
$var reg 1 F txe $end
$upscope $end
$upscope $end
$scope module rx_wbmaster $end
$var wire 1 2 clk $end
$var wire 1 3 data $end
$var wire 1 5 req $end
$var wire 1 7 reset $end
$var wire 1 G rxe $end
$var reg 1 H ack $end
$var reg 1 I r1 $end
$var reg 1 J r2 $end
$var reg 1 K r2d $end
$var reg 1 L rdata $end
$var reg 1 M vo $end
$upscope $end
$scope module tx_wbslave $end
$var wire 1 0 ack $end
$var wire 1 2 clk $end
$var wire 1 6 req $end
$var wire 1 8 reset $end
$var wire 1 : sdata $end
$var wire 1 $ snt $end
$var wire 1 N txe $end
$var wire 1 < vi $end
$var reg 1 O a1 $end
$var reg 1 P a2 $end
$var reg 1 Q a2d $end
$var reg 1 R data $end
$scope module txfsm $end
$var wire 1 S a2 $end
$var wire 1 2 clk $end
$var wire 1 8 reset $end
$var wire 1 < vi $end
$var reg 2 T current_state [1:0] $end
$var reg 2 U next_state [1:0] $end
$var reg 1 V req $end
$var reg 1 W txe $end
$upscope $end
$upscope $end
$scope module rx_wbslave $end
$var wire 1 2 clk $end
$var wire 1 4 data $end
$var wire 1 6 req $end
$var wire 1 8 reset $end
$var wire 1 X rxe $end
$var reg 1 Y ack $end
$var reg 1 Z r1 $end
$var reg 1 [ r2 $end
$var reg 1 \ r2d $end
$var reg 1 ] rdata $end
$var reg 1 ^ vo $end
$upscope $end
$upscope $end
$upscope $end
$enddefinitions $end
#0
$dumpvars
0^
0]
0\
0[
0Z
0Y
0X
0W
0V
b1 U
b0 T
0S
0R
0Q
0P
0O
0N
0M
0L
0K
0J
0I
0H
0G
0F
0E
b1 D
b0 C
0B
0A
0@
0?
0>
0=
0<
0;
x:
x9
18
17
06
05
04
03
02
01
00
0/
0.
0-
x,
x+
1*
1)
0(
0'
0&
0%
0$
0#
0"
0!
$end
#100
1(
12
1'
11
#200
0(
02
0'
01
0*
08
0)
07
#300
1W
1N
1F
1=
b1 T
b1 C
1(
12
1'
11
1,
1:
1+
19
#400
b10 U
b10 D
0(
02
0'
01
1.
1<
1-
1;
#500
1V
16
1E
15
1R
14
b10 T
1A
13
b10 C
1(
12
1'
11
#600
0(
02
0'
01
0.
0<
0-
0;
#700
1Z
1I
1(
12
1'
11
#800
0(
02
0'
01
#900
1X
1G
1[
1J
1(
12
1'
11
#1000
0(
02
0'
01
#1100
0X
0G
1^
1%
1Y
10
1\
1]
1"
1M
1&
1H
1/
1K
1L
1!
1(
12
1'
11
#1200
0(
02
0'
01
#1300
0^
0%
1O
0M
0&
1>
1(
12
1'
11
#1400
0(
02
0'
01
#1500
b1 U
1$
b1 D
1#
1P
1S
1?
1B
1(
12
1'
11
#1600
0(
02
0'
01
#1700
0$
0#
0V
06
0E
05
1Q
b1 T
1@
b1 C
1(
12
1'
11
#1800
0(
02
0'
01
#1900
0Z
0I
1(
12
1'
11
#2000
0(
02
0'
01
#2100
0[
0J
1(
12
1'
11
#2200
0(
02
0'
01
#2300
0Y
00
0\
0H
0/
0K
1(
12
1'
11
#2400
0(
02
0'
01
#2500
0O
0>
1(
12
1'
11
#2600
0(
02
0'
01
#2700
0P
0S
0?
0B
1(
12
1'
11
#2800
0(
02
0'
01
#2900
0Q
0@
1(
12
1'
11
