twoFF4phase/def.v
parameter  DATA_WIDTH = 8,
           DATA_MSB = DATA_WIDTH-1,
           DATA = 8'b1010_1111;

trunk/twoFF_4phase_slow_highlevel/txrx.v
`include "timescale.v"
module tx (/*AUTOARG*/
	   // Outputs
	   snt, req, data,
	   // Inputs
	   vi, ack, clk, reset, sdata
	   );
`include "def.v"
   output snt, req;
   output [DATA_MSB:0] data;
   input 	       vi, ack, clk, reset;
   input [DATA_MSB:0]  sdata;
   
   /*AUTOREG*/
   // Beginning of automatic regs (for this module's undeclared outputs)
   reg [DATA_MSB:0]    data;
   wire 	       req;
   wire 	       snt;
   // End of automatics
   
   reg 		       a2, a1, a2d;
   wire 	       vi, txe;
   
   txfsmslow txfsm(.txe(txe), .req(req), .vi(vi), .a2(a2), .clk(clk), .reset(reset));
   
   always @(posedge clk or posedge reset) begin
      if(reset) begin
	 data <=  {(1+(DATA_MSB)){1'b0}};
	 a1 <= 1'b0;
	 a2 <= 1'b0;
	 a2d <= 1'b0;
      end else begin
	 if(txe) begin
	    data <= sdata;
	 end
	 a1 <= ack;
	 a2 <= a1;
	 a2d <= a2;	
      end     
   end // always @ (posedge clk or posedge reset)
   
   assign snt = a2 & (~a2d);  
   
endmodule // tx

module rx (/*AUTOARG*/
	   // Outputs
	   ack, vo, rdata,
	   // Inputs
	   req, clk, reset, data
	   );
`include "def.v"
   
   output ack, vo;
   output [DATA_MSB:0] rdata;
   input 	       req, clk, reset;   
   input [DATA_MSB:0]  data;
   
   /*AUTOREG*/
   // Beginning of automatic regs (for this module's undeclared outputs)
   reg 		       ack;
   reg [DATA_MSB:0]    rdata;
   reg 		       vo;
   // End of automatics
   //wire [DATA_MSB:0]	rdata;
   reg 		       r1, r2, r2d;
   
   always @(posedge clk or posedge reset) begin
      if(reset) begin
	 rdata <=  {(1+(DATA_MSB)){1'b0}};
	 r1 <= 1'b0;
	 r2 <= 1'b0;
	 r2d <= 1'b0;
	 ack <= 1'b0;
	 vo <= 1'b0;	 
      end else begin
	 if(rxe) begin
	    rdata <= data;	    
	 end
	 r1 <= req;
	 r2 <= r1;
	 r2d <= r2;	
	 ack <= r2;
	 vo <= rxe;	 
      end
   end // rx
   
   /*always @* begin
    rdata = rdata1;
   end*/
   assign rxe = r2 & (~r2d);     
endmodule // rx

twoFF_4phase_slow_highlevel/txfsmslow.v
`include "timescale.v"
module txfsmslow(/*AUTOARG*/
		 // Outputs
		 txe, req,
		 // Inputs
		 vi, clk, a2, reset
		 );
`include "def.v"

   output txe, req;
   input  vi, clk, a2, reset;
   
   parameter  rst = 2'b00;  // Asynchronous reset state
   parameter  wdata = 2'b01;  // Wait for the input 'v'
   parameter  wack = 2'b10; // Data is on the bus, send the request to receiver (this is push synchronizer)
   //parameter  waiting = 2'b11; // Waiting for the deassertion of ack
   
   /*AUTOREG*/
   // Beginning of automatic regs (for this module's undeclared outputs)
   reg 	  req;
   reg 	  txe;
   // End of automatics
   reg [1:0] current_state, next_state;   
   
   /*This task handles the transmitter state machine*/
   
   always @(posedge clk or posedge reset) begin        
      if(reset) begin
	 current_state <= rst;
      end else begin
	 current_state <= next_state;
      end
   end
   
   always @(*) begin
      next_state = current_state;
      case(current_state) 
	rst: begin
	   txe = 1'b0;
	   req = 1'b0;	      
	   next_state = wdata;	    
	end
	
	wdata: begin
	   req = 1'b0;
	   txe = 1'b1;	      
	   if(vi == 1'b1 && a2 == 1'b0) begin 		      
	      next_state = wack;
	   end else if (vi == 1'b0 || a2 == 1'b1) begin
	      next_state = wdata;
	   end
	end
	
	wack: begin
	   req = 1'b1;
	   txe = 1'b1;
	   if(a2 == 1'b1) begin		    
	      next_state = wdata;   
	      end else if (a2 == 1'b0) begin
		 next_state = wack;		 
	      end	    
	end
	
	default: begin	 
	   req = 1'b0;
	   txe = 1'b0;
	   next_state = wdata;	    
	end	
      endcase // case (current_state)        
   end // always @ (*)
   
endmodule // txfsm_slow

trunk/twoFF_4phase_slow_highlevel/txrx_sync.v
`include "timescale.v"
module txrxsync(/*AUTOARG*/
		// Outputs
		vo, snt, rdata,
		// Inputs
		vi, clk_tx, clk_rx, reset, sdata
		);
`include "def.v"
   
   output vo, snt;
   output [DATA_MSB:0] rdata;
   input 	       vi, clk_tx, clk_rx, reset;
   input [DATA_MSB:0]  sdata;
   
   /*AUTOREG*/
   // Beginning of automatic regs (for this module's undeclared outputs)
   wire [DATA_MSB:0]   rdata;
   // End of automatics
   
   wire [DATA_MSB:0]   data;
   wire 	       req, ack;   
   
   /*Instantiation of tx and rx modules*/
   tx tx_U0(/*AUTOINST*/
	    // Outputs
	    .snt			(snt),
	    .req			(req),
	    .data			(data[DATA_MSB:0]),
	    // Inputs
	    .vi				(vi),
	    .ack			(ack),
	    .clk			(clk_tx),
	    .reset			(reset),
	    .sdata			(sdata[DATA_MSB:0]));
   rx rx_U1(/*AUTOINST*/
	    // Outputs
	    .ack			(ack),
	    .vo				(vo),
	    .rdata			(rdata[DATA_MSB:0]),
	    // Inputs
	    .req			(req),
	    .clk			(clk_rx),
	    .reset			(reset),
	    .data			(data[DATA_MSB:0]));   
   
endmodule // txrxsync

LDL/wb_LDLinp_gpio/sync_tb.v
`include "timescale.v"
module sync_tb();
`include "def.v"
   
   wire [DATA_MSB:0]  outs;
   wire 	      vo;
   reg [DATA_MSB:0]   data_core;
   reg 		      clk1, clk2, reset, vi;
   
   
   txrxsync txrxsync_U0(.snt(snt), .vo(vo), .rdata(outs), .vi(vi), .clk_tx(clk1), .clk_rx(clk2), .reset(reset), .sdata(data_core));
   
   
   initial        
     clk1 = 1'b0;
   always
     #1 clk1 = ~clk1; //tx-clk
   
   initial        
     clk2 = 1'b0;
   always
     #1 clk2 = ~clk2; //rx-clk
   
   initial
     begin
	$dumpvars;
        #1 vi = 1'b0;
	#1 reset = 1'b1;
        #3 reset = 1'b0;
        repeat(1) begin
           
	   #1 data_core = 8'b1111_1111; 	        	
           #1 vi = 1'b1;
           #2 vi = 1'b0;
	   
        end
	
        #250 $finish;
     end
   
endmodule // sync_tb

twoFF_4phase_slow_highlevel/dump.vcd
$date
	Mon Mar  5 16:55:43 2012
$end
$version
	Icarus Verilog
$end
$timescale
	10ps
$end
$scope module sync_tb $end
$var wire 8 ! outs [7:0] $end
$var wire 1 " snt $end
$var wire 1 # vo $end
$var reg 1 $ clk1 $end
$var reg 1 % clk2 $end
$var reg 8 & data_core [7:0] $end
$var reg 1 ' reset $end
$var reg 1 ( vi $end
$scope module txrxsync_U0 $end
$var wire 1 ) ack $end
$var wire 1 * clk_rx $end
$var wire 1 + clk_tx $end
$var wire 8 , data [7:0] $end
$var wire 8 - rdata [7:0] $end
$var wire 1 . req $end
$var wire 1 / reset $end
$var wire 8 0 sdata [7:0] $end
$var wire 1 " snt $end
$var wire 1 1 vi $end
$var wire 1 # vo $end
$scope module tx_U0 $end
$var wire 1 ) ack $end
$var wire 1 + clk $end
$var wire 1 . req $end
$var wire 1 / reset $end
$var wire 8 2 sdata [7:0] $end
$var wire 1 " snt $end
$var wire 1 3 txe $end
$var wire 1 1 vi $end
$var reg 1 4 a1 $end
$var reg 1 5 a2 $end
$var reg 1 6 a2d $end
$var reg 8 7 data [7:0] $end
$scope module txfsm $end
$var wire 1 8 a2 $end
$var wire 1 + clk $end
$var wire 1 / reset $end
$var wire 1 1 vi $end
$var reg 2 9 current_state [1:0] $end
$var reg 2 : next_state [1:0] $end
$var reg 1 ; req $end
$var reg 1 < txe $end
$upscope $end
$upscope $end
$scope module rx_U1 $end
$var wire 1 * clk $end
$var wire 8 = data [7:0] $end
$var wire 1 . req $end
$var wire 1 / reset $end
$var wire 1 > rxe $end
$var reg 1 ? ack $end
$var reg 1 @ r1 $end
$var reg 1 A r2 $end
$var reg 1 B r2d $end
$var reg 8 C rdata [7:0] $end
$var reg 1 D vo $end
$upscope $end
$upscope $end
$upscope $end
$enddefinitions $end
#0
$dumpvars
xD
bx C
xB
xA
x@
x?
x>
bx =
x<
x;
bx :
bx 9
x8
bx 7
x6
x5
x4
x3
bx 2
x1
bx 0
x/
x.
bx -
bx ,
0+
0*
x)
x(
x'
bx &
0%
0$
x#
x"
bx !
$end
#100
b1 :
0<
03
0;
0.
0(
01
1%
1*
1$
1+
#200
0>
0"
b1 :
0D
0#
0?
0)
0B
0A
0@
b0 C
b0 !
b0 -
06
05
08
04
b0 7
b0 ,
b0 =
b0 9
1'
1/
0%
0*
0$
0+
#300
1%
1*
1$
1+
#400
0%
0*
0$
0+
#500
1<
13
b1 9
1%
1*
1$
1+
0'
0/
#600
0%
0*
0$
0+
b11111111 &
b11111111 0
b11111111 2
#700
1;
1.
b10 9
b11111111 7
b11111111 ,
b11111111 =
b10 :
1%
1*
1$
1+
1(
11
#800
0%
0*
0$
0+
#900
1@
1%
1*
1$
1+
0(
01
#1000
0%
0*
0$
0+
#1100
1>
1A
1%
1*
1$
1+
#1200
0%
0*
0$
0+
#1300
0>
1D
1#
1?
1)
1B
b11111111 C
b11111111 !
b11111111 -
1%
1*
1$
1+
#1400
0%
0*
0$
0+
#1500
0D
0#
14
1%
1*
1$
1+
#1600
0%
0*
0$
0+
#1700
b1 :
1"
15
18
1%
1*
1$
1+
#1800
0%
0*
0$
0+
#1900
0"
0;
0.
b1 9
16
1%
1*
1$
1+
#2000
0%
0*
0$
0+
#2100
0@
1%
1*
1$
1+
#2200
0%
0*
0$
0+
#2300
0A
1%
1*
1$
1+
#2400
0%
0*
0$
0+
#2500
0?
0)
0B
1%
1*
1$
1+
#2600
0%
0*
0$
0+
#2700
04
1%
1*
1$
1+
#2800
0%
0*
0$
0+
#2900
05
08
1%
1*
1$
1+
#3000
0%
0*
0$
0+
#3100
06
1%
1*
1$
1+
