twoFF4phase/def.v
parameter  DATA_WIDTH = 8,
           DATA_MSB = DATA_WIDTH-1,
           DATA = 8'b1010_1111;

trunk/twoFF4phase/dff.v
module dff(/*AUTOARG*/
   // Outputs
   q,
   // Inputs
   d, clk, reset
   );

   input d,clk,reset;
   output q;
   /*AUTOREG*/
   // Beginning of automatic regs (for this module's undeclared outputs)
   reg			q;
   // End of automatics

   /*AUTOWIRE*/
   always @(posedge clk or posedge reset) begin
      if(reset) begin
	 q <= 1'b0; //using non blocking assignments for the sequential logic
      end else begin
	q <= d;
      end
   end

endmodule // DFF

twoFF4phase/rxfsm.v
module receiver(/*AUTOARG*/
   // Outputs
   output_rx, ack, d,
   // Inputs
   clk, reset, req, input_rx
   );
`include "def.v"

   input                clk, reset, req;   
   input [DATA_MSB:0]   input_rx; //Data input from other core
   output [DATA_MSB:0]  output_rx; //Data received
   output               ack, d;

   /*AUTOREG*/
   // Beginning of automatic regs (for this module's undeclared outputs)
   reg			ack;
   reg			d;
   reg [DATA_MSB:0]	output_rx;
   // End of automatics

   reg 			r3;   
   wire 		r1, r2;
   reg statemachine;
     
   parameter  rst = 2'b00;  // Asynchronous reset state
   parameter  idle = 2'b01;  // Wait for the input 'v'
   parameter  acknowledge = 2'b10; // Data is on the bus, send the request to receiver (this is push synchronizer)
   parameter  waiting = 2'b11; // Waiting for the deassertion of ack
   
   reg[1:0]  current_state, next_state;
   /* Instantiate the two(can be extended depending on MTBF requirment) flip flops for the req input- this avoids metastability till MTBF*/
   dff  dff1(.q(r1), .d(req), .clk(clk), .reset(reset));
   dff  dff2(.q(r2), .d(r1), .clk(clk), .reset(reset));
   
   always @(posedge clk or posedge reset) begin
      r3 <= r2;
      d <= (!r3) & r2;
      if(reset) begin
	 output_rx <= 0;
         statemachine <= 1'b0;	 
      end else begin
	 if(r2 == 1'b1) begin
	    output_rx <= input_rx; /* Latch the data into Rx-buffer*/	  
	    statemachine <= 1'b1;    
	 end 
      end
   end 
   
    always@(posedge clk or posedge reset) begin
      
       if(reset) begin
	  current_state <= rst;
       end else begin
	  current_state <= next_state;
       end
    end
   
   always @(*) begin
      next_state = current_state;
      if(statemachine) begin        
      case(current_state)
	 rst: begin
	    next_state = idle;
	    ack = 1'b0;
	 end

	 idle: begin
	    if(r2 == 1'b1) begin 
	       next_state = acknowledge;
	       ack = 1'b1;	       
	    end
	 end

	  acknowledge: begin
	    if(r2 == 1'b0) begin
	       next_state = idle;
	       ack = 1'b0;	       
	    end	    
	 end

	 default: begin
	    next_state = idle;
	    ack = 1'b0;	    
	 end	
      endcase // case (current_state)
      end
   end // always @ (*)

endmodule // receiver

twoFF4phase/txfsm.v
module transmitter(/*AUTOARG*/
   // Outputs
   output_tx, req, f,
   // Inputs
   clk, v, reset, ack, input_tx
   );
`include "def.v"

   parameter  DATA_WIDTH = `DATA_WIDTHS,
           DATA_MSB = DATA_WIDTH-1,
           DATA = `DATAS;

   input                clk,v,reset,ack;
   input [DATA_MSB:0]   input_tx; // Plug-in the data that has to be transmitted to other core
   output [DATA_MSB:0]  output_tx; // Tx-buffer
   output               req,f;

   /*AUTOREG*/
   // Beginning of automatic regs (for this module's undeclared outputs)
   reg			f;
   reg [DATA_MSB:0]	output_tx;
   reg			req;
   // End of automatics

   reg 	     a3;   
   wire      a1, a2;

   parameter  rst = 2'b00;  // Asynchronous reset state
   parameter  idle = 2'b01;  // Wait for the input 'v'
   parameter  request = 2'b10; // Data is on the bus, send the request to receiver (this is push synchronizer)
   parameter  waiting = 2'b11; // Waiting for the deassertion of ack
   
   reg[1:0]  current_state, next_state;   
   reg statemachine;

   /* Instantiate the two(can be extended depending on MTBF requirment) flip flops for the ack input- this avoids metastability till MTBF */
   dff  dff1(.q(a1), .d(ack), .clk(clk), .reset(reset));
   dff  dff2(.q(a2), .d(a1), .clk(clk), .reset(reset));
   
   always @(posedge clk or posedge reset) begin
      a3 <= a2;
      f <= (! a3) & a2;
      if(reset) begin
	 output_tx <= 0;
         statemachine <= 1'b0;	 
      end else begin
	 if (v == 1'b1) begin
	    output_tx <= input_tx; // Put the data into transmit data buffer	   
	    statemachine <= 1'b1;
	 end	 
      end
   end   

   
/*This task handles the transmitter state machine*/
     
    always @(posedge clk or posedge reset) begin        
       if(reset) begin
	  current_state <= rst;
       end else begin
	  current_state <= next_state;
       end
    end
   
   always @(*) begin
      next_state = current_state;
      if(statemachine) begin
      case(current_state) 
	 rst: begin
	    next_state = idle;
	    req = 1'b0;
	 end

	 idle: begin
	    if(v == 1'b1) begin 
	       next_state = request;
	       req = 1'b1;	       
	    end
	 end

	 request: begin
	    if(a2 == 1'b1) begin
	       next_state = waiting;
	       req = 1'b0;	       
	    end	    
	 end

	 waiting: begin
	    if(a2 == 1'b0) begin
	       next_state = idle;
	    end   
	 end
	
	 default: begin
	    next_state = idle;
	    req = 1'b0;	    
	 end	
      endcase // case (current_state)
      end  
   end // always @ (*)


endmodule // transmitter

twoFF4phase/sync.v
module sync_multi(/*AUTOARG*/
   // Outputs
   out_data, f, d,
   // Inputs
   in_data, v, clk1, clk2, reset
   );

`include "def.v"

   parameter  DATA_WIDTH = `DATA_WIDTHS,
     DATA_MSB = DATA_WIDTH-1,
     DATA = `DATAS;

   output [DATA_MSB:0] out_data;
   output 	       f, d;
   input [DATA_MSB:0]  in_data;
   input 	       v, clk1, clk2, reset;

   /*AUTOREG*/
   // Beginning of automatic regs (for this module's undeclared outputs)
   reg			d;
   reg			f;
   wire [DATA_MSB:0]	out_data;
   // End of automatics
   wire [DATA_MSB:0]   data;   
   wire ack1, req1, f1, d1;
 
   transmitter tx1(.output_tx(data), .req(req1), .f(f1), .clk(clk1), .v(v), .reset(reset), .ack(ack1), .input_tx(in_data));
   receiver rx1(.output_rx(out_data), .ack(ack1), .d(d1), .clk(clk2), .reset(reset), .req(req1), .input_rx(data));
        always @* begin
                f =f1;
                d =d1;
        end           
endmodule // sync_multi

twoFF4phase/sync_tb.v
module sync_tb();
`include "def.v"

parameter  DATA_WIDTH = `DATA_WIDTHS,
           DATA_MSB = DATA_WIDTH-1,
           DATA = `DATAS;

   wire [DATA_MSB:0]  outs;
   wire f, d;
   reg [DATA_MSB:0] data_core;
   reg 		    clk1, clk2, reset, v;
 
   sync_multi syncss1(.out_data(outs), .f(f), .d(d), .in_data(data_core), .v(v), .clk1(clk1), .clk2(clk2), .reset(reset));
   
   initial        
     clk1 = 1'b0;
   always
     #1 clk1 = ~clk1;

   initial        
     clk2 = 1'b0;
   always
     #2 clk2 = ~clk2;

   initial
     begin
     $dumpvars;
	#1 reset = 1'b1;
	#1 data_core = DATA;
	#1 reset = 1'b0;
	
        #2 v = 1'b1;
        #10 v = 1'b0;
        #5 data_core = 8'b0011_0101;
        #1 v = 1'b1;
        #10 v = 1'b0;
        #20 data_core = 8'b1111_1111;
        #21 v = 1'b1;
        #25 v = 1'b0;
        #5 reset = 1'b1;

        #250 $finish;
     end
   
endmodule // sync_tb

twoFF4phase/dump.vcd
$date
	Wed Feb 15 16:10:16 2012
$end
$version
	Icarus Verilog
$end
$timescale
	1s
$end
$scope module sync_tb $end
$var wire 1 ! d $end
$var wire 1 " f $end
$var wire 8 # outs [7:0] $end
$var reg 1 $ clk1 $end
$var reg 1 % clk2 $end
$var reg 8 & data_core [7:0] $end
$var reg 1 ' reset $end
$var reg 1 ( v $end
$scope module syncss1 $end
$var wire 1 ) ack1 $end
$var wire 1 * clk1 $end
$var wire 1 + clk2 $end
$var wire 1 , d1 $end
$var wire 8 - data [7:0] $end
$var wire 1 . f1 $end
$var wire 8 / in_data [7:0] $end
$var wire 8 0 out_data [7:0] $end
$var wire 1 1 req1 $end
$var wire 1 2 reset $end
$var wire 1 3 v $end
$var reg 1 4 d $end
$var reg 1 5 f $end
$scope module tx1 $end
$var wire 1 6 a1 $end
$var wire 1 7 a2 $end
$var wire 1 ) ack $end
$var wire 1 * clk $end
$var wire 8 8 input_tx [7:0] $end
$var wire 1 2 reset $end
$var wire 1 3 v $end
$var reg 1 9 a3 $end
$var reg 2 : current_state [1:0] $end
$var reg 1 ; f $end
$var reg 2 < next_state [1:0] $end
$var reg 8 = output_tx [7:0] $end
$var reg 1 > req $end
$var reg 1 ? statemachine $end
$scope module dff1 $end
$var wire 1 * clk $end
$var wire 1 ) d $end
$var wire 1 2 reset $end
$var reg 1 @ q $end
$upscope $end
$scope module dff2 $end
$var wire 1 * clk $end
$var wire 1 6 d $end
$var wire 1 2 reset $end
$var reg 1 A q $end
$upscope $end
$upscope $end
$scope module rx1 $end
$var wire 1 + clk $end
$var wire 8 B input_rx [7:0] $end
$var wire 1 C r1 $end
$var wire 1 D r2 $end
$var wire 1 1 req $end
$var wire 1 2 reset $end
$var reg 1 E ack $end
$var reg 2 F current_state [1:0] $end
$var reg 1 G d $end
$var reg 2 H next_state [1:0] $end
$var reg 8 I output_rx [7:0] $end
$var reg 1 J r3 $end
$var reg 1 K statemachine $end
$scope module dff1 $end
$var wire 1 + clk $end
$var wire 1 1 d $end
$var wire 1 2 reset $end
$var reg 1 L q $end
$upscope $end
$scope module dff2 $end
$var wire 1 + clk $end
$var wire 1 C d $end
$var wire 1 2 reset $end
$var reg 1 M q $end
$upscope $end
$upscope $end
$upscope $end
$upscope $end
$enddefinitions $end
#0
$dumpvars
xM
xL
xK
xJ
bx I
bx H
xG
bx F
xE
xD
xC
bx B
xA
x@
x?
x>
bx =
bx <
x;
bx :
x9
bx 8
x7
x6
x5
x4
x3
x2
x1
bx 0
bx /
x.
bx -
x,
0+
0*
x)
x(
x'
bx &
0%
0$
bx #
x"
x!
$end
#1
b0 <
0L
0C
0M
0D
0K
b0 I
b0 #
b0 0
0@
06
0A
07
0?
b0 =
b0 -
b0 B
b0 :
1'
12
1$
1*
#2
b0 H
b0 F
b10101111 &
b10101111 /
b10101111 8
0$
0*
1%
1+
#3
x@
x6
0'
02
1$
1*
#4
0$
0*
0%
0+
#5
0>
01
b1 <
05
0"
xA
x7
1?
b10101111 =
b10101111 -
b10101111 B
0;
0.
09
1$
1*
1(
13
#6
0$
0*
1%
1+
#7
x5
x"
1>
11
b10 <
x;
x.
x9
b1 :
1$
1*
#8
0$
0*
0%
0+
#9
b10 :
1$
1*
#10
1L
1C
0$
0*
1%
1+
#11
1$
1*
#12
0$
0*
0%
0+
#13
1$
1*
#14
1M
1D
0$
0*
1%
1+
#15
1$
1*
0(
03
#16
0$
0*
0%
0+
#17
1$
1*
#18
0E
0)
b1 H
1K
1J
b10101111 I
b10101111 #
b10101111 0
0$
0*
1%
1+
#19
0@
06
1$
1*
#20
0$
0*
0%
0+
b110101 &
b110101 /
b110101 8
#21
0A
07
b110101 =
b110101 -
b110101 B
1$
1*
1(
13
#22
04
0!
1E
1)
b10 H
0G
0,
b110101 I
b110101 #
b110101 0
b1 F
0$
0*
1%
1+
#23
05
0"
0;
0.
09
1@
16
1$
1*
#24
0$
0*
0%
0+
#25
0>
01
b11 <
1A
17
1$
1*
#26
0L
0C
b10 F
0$
0*
1%
1+
#27
15
1"
1;
1.
19
b11 :
1$
1*
#28
0$
0*
0%
0+
#29
05
0"
0;
0.
1$
1*
#30
0E
0)
b1 H
0M
0D
0$
0*
1%
1+
#31
0@
06
1$
1*
0(
03
#32
0$
0*
0%
0+
#33
b1 <
0A
07
1$
1*
#34
b1 F
0$
0*
1%
1+
#35
b1 :
1$
1*
#36
0$
0*
0%
0+
#37
1$
1*
#38
0$
0*
1%
1+
#39
1$
1*
#40
0$
0*
0%
0+
#41
1$
1*
#42
0$
0*
1%
1+
#43
1$
1*
#44
0$
0*
0%
0+
#45
1$
1*
#46
0$
0*
1%
1+
#47
1$
1*
#48
0$
0*
0%
0+
#49
1$
1*
#50
0$
0*
1%
1+
#51
1$
1*
b11111111 &
b11111111 /
b11111111 8
#52
0$
0*
0%
0+
#53
1$
1*
#54
0$
0*
1%
1+
#55
1$
1*
#56
0$
0*
0%
0+
#57
1$
1*
#58
0$
0*
1%
1+
#59
1$
1*
#60
0$
0*
0%
0+
#61
1$
1*
#62
0$
0*
1%
1+
#63
1$
1*
#64
0$
0*
0%
0+
#65
1$
1*
#66
0$
0*
1%
1+
#67
1$
1*
#68
0$
0*
0%
0+
#69
1$
1*
#70
0$
0*
1%
1+
#71
1$
1*
#72
1>
11
b10 <
0$
0*
0%
0+
1(
13
#73
b11111111 =
b11111111 -
b11111111 B
09
b10 :
1$
1*
#74
1L
1C
0$
0*
1%
1+
#75
1$
1*
#76
0$
0*
0%
0+
#77
1$
1*
#78
1E
1)
b10 H
1M
1D
0$
0*
1%
1+
#79
1@
16
1$
1*
#80
0$
0*
0%
0+
#81
0>
01
b11 <
1A
17
1$
1*
#82
b11111111 I
b11111111 #
b11111111 0
0L
0C
b10 F
0$
0*
1%
1+
#83
15
1"
1;
1.
19
b11 :
1$
1*
#84
0$
0*
0%
0+
#85
05
0"
0;
0.
1$
1*
#86
0E
0)
b1 H
0M
0D
0$
0*
1%
1+
#87
0@
06
1$
1*
#88
0$
0*
0%
0+
#89
b1 <
0A
07
1$
1*
#90
b1 F
0$
0*
1%
1+
#91
1>
11
b10 <
09
b1 :
1$
1*
#92
0$
0*
0%
0+
#93
b10 :
1$
1*
#94
1L
1C
0$
0*
1%
1+
#95
1$
1*
#96
0$
0*
0%
0+
#97
1$
1*
0(
03
#98
1E
1)
b10 H
1M
1D
0$
0*
1%
1+
#99
1@
16
1$
1*
#100
0$
0*
0%
0+
#101
0>
01
b11 <
1A
17
1$
1*
#102
b0 H
b10 <
b0 F
0L
0C
0M
0D
0K
b0 I
b0 #
b0 0
0?
b0 =
b0 -
b0 B
0A
07
0@
06
0$
0*
1%
1+
1'
12
#103
b0 <
b0 :
1$
1*
