twoFF4phase/def.v
parameter  DATA_WIDTH = 8,
           DATA_MSB = DATA_WIDTH-1,
           DATA = 8'b1010_1111;

twoFF_slow/txfsmslow.v
module txfsmslow(/*AUTOARG*/
   // Outputs
   txe, req,
   // Inputs
   vi, clk, a2, reset
   );
`include "def.v"

   output txe, req;
   input  vi, clk, a2, reset;
   
   parameter  rst = 2'b00;  // Asynchronous reset state
   parameter  wdata = 2'b01;  // Wait for the input 'v'
   parameter  wack = 2'b10; // Data is on the bus, send the request to receiver (this is push synchronizer)
   //parameter  waiting = 2'b11; // Waiting for the deassertion of ack

   /*AUTOREG*/
   // Beginning of automatic regs (for this module's undeclared outputs)
   reg			req;
   reg			txe;
   // End of automatics
   reg [1:0] 		current_state, next_state;   
   
   /*This task handles the transmitter state machine*/
   
    always @(posedge clk or posedge reset) begin        
       if(reset) begin
	  current_state <= rst;
       end else begin
	  current_state <= next_state;
       end
    end
   
   always @(*) begin
      next_state = current_state;
	 case(current_state) 
	   rst: begin
	      txe = 1'b0;
	      req = 1'b0;	      
	      next_state = wdata;	    
	   end
	   
	   wdata: begin
	      req = 1'b0;
	      txe = 1'b1;	      
	      if(vi == 1'b1 && a2 == 1'b0) begin 		      
		 next_state = wack;
	      end else if (vi == 1'b0 || a2 == 1'b1) begin
		  next_state = wdata;
	      end
	   end
	   
	   wack: begin
	      req = 1'b1;
	      txe = 1'b1;
	      if(a2 == 1'b1) begin		    
		 next_state = wdata;   
	      end else if (a2 == 1'b0) begin
		 next_state = wack;		 
	      end	    
	   end
	   
	   default: begin	 
	      req = 1'b0;
	      txe = 1'b0;
	      next_state = wdata;	    
	   end	
	 endcase // case (current_state)        
   end // always @ (*)

endmodule // txfsm_slow

trunk/twoFF_slow/transmitter.v
module transmitterslow(/*AUTOARG*/
   // Outputs
   snt, req, data,
   // Inputs
   vi, ack, sdata, clk, reset
   );
`include "def.v"

   output snt, req;
   output [DATA_MSB:0] data;
   input 	       vi, ack, clk, reset;
   input [DATA_MSB:0]  sdata;

   /*AUTOREG*/
   // Beginning of automatic regs (for this module's undeclared outputs)
   reg [DATA_MSB:0]	data;
   reg			req;
   reg			snt;
   // End of automatics
   wire [DATA_MSB:0]   data1;
   wire 	       snt1;
   wire 	       req1;
   wire 	       txe;
   wire 	       a2;      
   wire 	       a1;
   
   /*Instantiate the individual blocks to form complete transmitter */

   regdataen regt (.q(data1), .a(sdata), .en(txe), .reset(reset), .clk(clk));
   txfsmslow txfsm(.txe(txe), .req(req1), .vi(vi), .a2(a2), .clk(clk), .reset(reset));
   dffs f1(.q(a1), .d(ack), .clk(clk), .reset(reset));
   dffs f2(.q(a2), .d(a1), .clk(clk), .reset(reset));
   dffs f3(.q(a3), .d(a2), .clk(clk), .reset(reset));
   and2 and1(.q(snt1), .a(~a3), .b(a2));   
   
   always @* begin
      data = data1;
      snt = snt1;
      req = req1;
   end
endmodule // transmitter

twoFF_slow/receiver.v
module receiverslow(/*AUTOARG*/
   // Outputs
   ack, vo, rdata,
   // Inputs
   req, clk, reset, data
   );
`include "def.v"
   
   output ack, vo;
   output [DATA_MSB:0] rdata;
   input 	       req, clk, reset;   
   input [DATA_MSB:0]  data;
   
   /*AUTOREG*/
   // Beginning of automatic regs (for this module's undeclared outputs)
   reg			ack;
   reg [DATA_MSB:0]	rdata;
   reg			vo;
   // End of automatics
   wire [DATA_MSB:0]   rdata1;
   wire 	       ack1;
   wire 	       vo1;
   wire 	       r1, r2, r3, r4;
   
   /*Instantiate the blocks to form complete receiver*/
   regdataen regr(.q(rdata1), .a(data), .en(r4), .reset(reset), .clk(clk));
   dffs f4(.q(r1), .d(req), .clk(clk), .reset(reset));
   dffs f5(.q(r2), .d(r1), .clk(clk), .reset(reset));
   dffs f6(.q(r3), .d(r2), .clk(clk), .reset(reset));
   dffs f7(.q(ack1), .d(r2), .clk(clk), .reset(reset));   
   dffs f8(.q(vo1), .d(r4), .clk(clk), .reset(reset));   
   and2 and3(.q(r4), .a(r2), .b(~r3));  
   
   always @* begin
         rdata = rdata1;
         ack = ack1;
         vo = vo1;
      end	 
endmodule // receiverslow

trunk/twoFF_slow/syncslow.v
module syncslow(/*AUTOARG*/
   // Outputs
   vo, snt, rdata,
   // Inputs
   vi, clk_tx, clk_rx, reset, sdata
   );
`include "def.v"

   output vo, snt;
   output [DATA_MSB:0] rdata;
   input 	       vi, clk_tx, clk_rx, reset;
   input [DATA_MSB:0]  sdata;
   
   /*AUTOREG*/
   // Beginning of automatic regs (for this module's undeclared outputs)
   reg [DATA_MSB:0]	rdata;
   reg			snt;
   reg			vo;
   // End of automatics
   wire [DATA_MSB:0] 	rdata1,data1;   
   wire 		req1, ack1, vo1, snt1;
   
   receiverslow rx(.ack(ack1), .vo(vo1), .rdata(rdata1), .req(req1), .reset(reset), .clk(clk_rx), .data(sdata));
   transmitterslow tx(.snt(snt1), .req(req1), .data(data1), .vi(vi), .ack(ack1), .sdata(sdata), .clk(clk_tx), .reset(reset));
   
   always @* begin
         snt = snt1;
         vo = vo1;
         rdata = rdata1;
   end
endmodule // syncslow

twoFF_slow/sync_tb.v
module sync_tb();
`include "def.v"

   wire [DATA_MSB:0]  outs;
   wire vo;
   reg [DATA_MSB:0] data_core;
   reg 		    clk1, clk2, reset, vi;
   reg [31:0] Mem [0:5]; 
   integer k;
 
   syncslow sync(.snt(snt), .vo(vo), .rdata(outs), .vi(vi), .clk_tx(clk1), .clk_rx(clk2), .reset(reset), .sdata(data_core));
   
   
   initial        
     clk1 = 1'b0;
   always
     #1 clk1 = ~clk1; //tx-clk

   initial        
     clk2 = 1'b0;
   always
     #1 clk2 = ~clk2; //rx-clk

   initial $readmemh("vectors.txt",Mem); 
   
  
   /*initial begin 
      #10; 
      $display("Contents of Mem after reading data file:"); 
      for (k=0; k<6; k=k+1) $display("%d:%h",k,Mem[k]); 
   end */

   initial
     begin
     $dumpvars;
   #1 vi = 1'b0;
	#1 reset = 1'b1; k = 1;
        #1 reset = 1'b0;
        repeat(1) begin
                
	        #1 data_core = 1111_1111; 	        	
                #1 vi = 1'b1;
                #5 vi = 1'b0;
                //k = k + 1;
        end

        #250 $finish;
     end
   
endmodule // sync_tb

twoFF_slow/basic_cells.v
/* This file contains all the basic elements required for this project. Each elements are defined in separate modules*/

/* D-Flip Flop*/
module dff(/*AUTOARG*/
   // Outputs
   q, q_bar,
   // Inputs
   d, clk, reset
   );

   parameter DELAY = 1;
   
   input d,clk,reset;
   output q, q_bar;

   reg 	  q_i;
 	  
   /*AUTOREG*/
  
   always @(posedge clk or posedge reset) begin
      if(reset) begin
	 q_i <= 1'b0; //using non blocking assignments for the sequential logic
      end else begin
	 q_i <= d;
      end
   end
  assign #DELAY q = q_i;
  assign #DELAY q_bar = ~q_i;   
endmodule // dff

/*NOT gate*/
module inv(/*AUTOARG*/
   // Outputs
   idash,
   // Inputs
   i
   );

   parameter DELAY = 1;

   output idash;
   input i;

   assign #DELAY idash = !i;   
endmodule // inv

/* 2 input AND gate*/
module and2(/*AUTOARG*/
   // Outputs
   q,
   // Inputs
   a, b
   );

   parameter DELAY = 1;

   output q;
   input  a, b;

   assign #DELAY q = a & b;
endmodule // and2

/* 3 input AND gate*/
module and3(/*AUTOARG*/
   // Outputs
   q,
   // Inputs
   a, b, c
   );

   parameter DELAY = 1;

   output q;
   input  a, b, c;

   assign #DELAY q = a & b & c;
endmodule // and3

/* 2 input OR gate*/
module or2 (/*AUTOARG*/
   // Outputs
   q,
   // Inputs
   a, b
   );

   parameter DELAY = 1;

   output q;
   input  a, b;

   assign #DELAY q = a | b;   
endmodule // or2

/* 2 input nor gate*/
module nor2(/*AUTOARG*/
   // Outputs
   q,
   // Inputs
   a, b
   );
   parameter DELAY = 1;

   output q;
   input  a, b;

   assign #DELAY q = ~ (a | b);
endmodule // nor2

/* 3 input OR gate*/
module or3( /*AUTOARG*/
   // Outputs
   q,
   // Inputs
   a, b, c
   );

   parameter DELAY = 1;

   output q;
   input  a, b, c;

   assign #DEALAY q = a | b | c;
endmodule // or3

/* 2 input EXOR gate*/ 
module xor2(/*AUTOARG*/
   // Outputs
   q,
   // Inputs
   a, b
   );
   
   parameter DELAY = 1;

   output q;
   input  a, b;

   assign #DELAY q = a ^ b;
endmodule // xor2

/* 3 input EXOR gate*/
module xor3(/*AUTOARG*/
   // Outputs
   q,
   // Inputs
   a, b, c
   );

   parameter DELAY = 1;

   output q;
   input  a, b, c;

   assign #DELAY q = a ^ b ^ c;   
endmodule // xor3

/* S-R latch built using NOR gates*/
module srlatch(/*AUTOARG*/
   // Outputs
   q, qbar,
   // Inputs
   s, r
   );

   parameter DELAY = 1;

   output q, qbar;
   input  s, r;

   /*AUTOREG*/
   // Beginning of automatic regs (for this module's undeclared outputs)
   reg			q;
   reg			qbar;
   // End of automatics
   wire qbar_i, q_i;
   nor2 norx(qbar_i, s, q_i);
   nor2 nory(q_i, r, qbar_i);  
        always @* begin
                qbar = #DELAY qbar_i;
                q = #DELAY q_i; 
        end  
   //assign #DELAY qbar =  qbar_i;
   //assign #DELAY q = q_i;      
endmodule // srlatch

   
/* Delay element*/
module delay(/*AUTOARG*/
   // Outputs
   q,
   // Inputs
   i
   );

   parameter DELAY = 1;

   output q;
   input  i;

   assign #DELAY q = i;
endmodule // delay

/* Muller-c element*/
module celement(/*AUTOARG*/
   // Outputs
   q,
   // Inputs
   a, b, reset
   );
   
   parameter DELAY = 1;
   output q;
   input  a, b, reset;

   /*AUTOREG*/
   // Beginning of automatic regs (for this module's undeclared outputs)
   reg			q;
   // End of automatics
   always @(*) begin
      if(reset) begin
	 q <= 0;	 
      end else if(a == b) begin
	 q <= #DELAY b;	 
      end            
   end
endmodule // celement
   
/* Data register with multiple buswidth*/
module regdata(/*AUTOARG*/
   // Outputs
   q,
   // Inputs
   a, clk, reset
   );
   `include "def.v"

   parameter DELAY = 1;

   output [DATA_MSB:0] q;
   input [DATA_MSB:0]  a;
   input 	       clk, reset;
   
   reg [DATA_MSB:0]    q_i;    
   
   always @(posedge clk or posedge reset) begin
      if(reset) begin
	 q_i <= 0;
      end else begin
	 q_i <= a;	 
      end      
   end
   assign #DELAY q = q_i;   
endmodule // regdata

/*T-flip flop */
module tff(/*AUTOARG*/
   // Outputs
   q, qbar,
   // Inputs
   t, clk, reset
   );

   parameter DELAY = 1;

   output q, qbar;
   input  t, clk, reset;

   reg 	  q_i;
   
   always@(posedge clk or posedge reset) begin
      if(reset) begin
	 q_i <= 1'b0;	
      end else if(t) begin
	 q_i <= ~q_i;	 
      end      
   end

   assign #DELAY q = q_i;
   assign #DELAY qbar = ~q_i;
endmodule // tff

/* MUX 2:1*/
module mux(/*AUTOARG*/
   // Outputs
   q,
   // Inputs
   a, s
   );

   parameter DELAY = 1;

   output q;
   input [1:0] a;
   input       s;

   assign #DELAY q = s ? a[1] : a[0];
endmodule // mux

/* Data register with multiple buswidth and enable input*/
module regdataen(/*AUTOARG*/
   // Outputs
   q,
   // Inputs
   a, en, reset, clk
   );
   `include "def.v"

   parameter DELAY = 1;

   output [DATA_MSB:0] q;
   input [DATA_MSB:0]  a;
   input 	       en, reset, clk;
   
   reg [DATA_MSB:0]    q_i;    
   
   always @(posedge en or posedge clk or posedge reset) begin
      if(reset) begin
	 q_i <= 0;
      end else if(en) begin
	 q_i <= a;	 
      end      
   end
   assign #DELAY q = q_i;   
endmodule // regdataen

/* Data register with multiple buswidth and enable + enable* input*/
module regdataenstar(/*AUTOARG*/
   // Outputs
   q,
   // Inputs
   a, en, reset, enstar, clk
   );
   `include "def.v"

   parameter DELAY = 1;

   output [DATA_MSB:0] q;
   input [DATA_MSB:0]  a;
   input 	       en, reset, enstar,clk;
   
   reg [DATA_MSB:0]    q_i;    
   
   always @(posedge en or posedge enstar or posedge clk or posedge reset ) begin
      if(reset) begin
	 q_i <= 0;
      end else if(en && enstar) begin
	 q_i <= a;	 
      end      
   end
   assign #DELAY q = q_i;   
endmodule // regdataenstar

/* Register with enable, enable star and async reset */
module regenstar(/*AUTOARG*/
   // Outputs
   q,
   // Inputs
   a, en, reset, enstar, clk
   );
 
   parameter DELAY = 1;

   output q;
   input  a;
   input  en, reset, enstar, clk;
   
   reg q_i;    
   
   always @(posedge en or posedge enstar or posedge clk or posedge reset) begin
      if(reset) begin
	 q_i <= 0;
      end else if(en && enstar) begin
	 q_i <= a;	 
      end      
   end
   assign #DELAY q = q_i;   
endmodule // regenstar

/* data flip flop without qbar */
module dffs(/*AUTOARG*/
   // Outputs
   q,
   // Inputs
   d, clk, reset
   );

   parameter DELAY = 1;
   
   input d,clk,reset;
   output q;

   reg 	  q_i;
 	  
   /*AUTOREG*/
  
   always @(posedge clk or posedge reset) begin
      if(reset) begin
	 q_i <= 1'b0; //using non blocking assignments for the sequential logic
      end else begin
	 q_i <= d;
      end
   end
  assign #DELAY q = q_i;
 
endmodule // dffs


/* Yet to be done :-) */
/* MUTEX element*/
/* D-Flip flop with Async reset and EN* */
/* Asynchronous Controllers for LDL*/

twoFF_slow/dump.vcd
$date
	Fri Feb 24 16:41:06 2012
$end
$version
	Icarus Verilog
$end
$timescale
	1s
$end
$scope module and3 $end
$var wire 1 ! a $end
$var wire 1 " b $end
$var wire 1 # c $end
$var wire 1 $ q $end
$upscope $end
$scope module celement $end
$var wire 1 % a $end
$var wire 1 & b $end
$var wire 1 ' reset $end
$var reg 1 ( q $end
$upscope $end
$scope module delay $end
$var wire 1 ) i $end
$var wire 1 * q $end
$upscope $end
$scope module dff $end
$var wire 1 + clk $end
$var wire 1 , d $end
$var wire 1 - q $end
$var wire 1 . q_bar $end
$var wire 1 / reset $end
$var reg 1 0 q_i $end
$upscope $end
$scope module inv $end
$var wire 1 1 i $end
$var wire 1 2 idash $end
$upscope $end
$scope module mux $end
$var wire 2 3 a [1:0] $end
$var wire 1 4 q $end
$var wire 1 5 s $end
$upscope $end
$scope module or2 $end
$var wire 1 6 a $end
$var wire 1 7 b $end
$var wire 1 8 q $end
$upscope $end
$scope module or3 $end
$var wire 1 9 DEALAY $end
$var wire 1 : a $end
$var wire 1 ; b $end
$var wire 1 < c $end
$var wire 1 = q $end
$upscope $end
$scope module regdata $end
$var wire 8 > a [7:0] $end
$var wire 1 ? clk $end
$var wire 8 @ q [7:0] $end
$var wire 1 A reset $end
$var reg 8 B q_i [7:0] $end
$upscope $end
$scope module regdataenstar $end
$var wire 8 C a [7:0] $end
$var wire 1 D clk $end
$var wire 1 E en $end
$var wire 1 F enstar $end
$var wire 8 G q [7:0] $end
$var wire 1 H reset $end
$var reg 8 I q_i [7:0] $end
$upscope $end
$scope module regenstar $end
$var wire 1 J a $end
$var wire 1 K clk $end
$var wire 1 L en $end
$var wire 1 M enstar $end
$var wire 1 N q $end
$var wire 1 O reset $end
$var reg 1 P q_i $end
$upscope $end
$scope module srlatch $end
$var wire 1 Q q_i $end
$var wire 1 R qbar_i $end
$var wire 1 S r $end
$var wire 1 T s $end
$var reg 1 U q $end
$var reg 1 V qbar $end
$scope module norx $end
$var wire 1 T a $end
$var wire 1 Q b $end
$var wire 1 R q $end
$upscope $end
$scope module nory $end
$var wire 1 S a $end
$var wire 1 R b $end
$var wire 1 Q q $end
$upscope $end
$upscope $end
$scope module sync_tb $end
$var wire 8 W outs [7:0] $end
$var wire 1 X snt $end
$var wire 1 Y vo $end
$var reg 1 Z clk1 $end
$var reg 1 [ clk2 $end
$var reg 8 \ data_core [7:0] $end
$var integer 32 ] k [31:0] $end
$var reg 1 ^ reset $end
$var reg 1 _ vi $end
$scope module sync $end
$var wire 1 ` ack1 $end
$var wire 1 a clk_rx $end
$var wire 1 b clk_tx $end
$var wire 8 c data1 [7:0] $end
$var wire 8 d rdata1 [7:0] $end
$var wire 1 e req1 $end
$var wire 1 f reset $end
$var wire 8 g sdata [7:0] $end
$var wire 1 h snt1 $end
$var wire 1 i vi $end
$var wire 1 j vo1 $end
$var reg 8 k rdata [7:0] $end
$var reg 1 l snt $end
$var reg 1 m vo $end
$scope module rx $end
$var wire 1 n ack1 $end
$var wire 1 a clk $end
$var wire 8 o data [7:0] $end
$var wire 1 p r1 $end
$var wire 1 q r2 $end
$var wire 1 r r3 $end
$var wire 1 s r4 $end
$var wire 8 t rdata1 [7:0] $end
$var wire 1 e req $end
$var wire 1 f reset $end
$var wire 1 u vo1 $end
$var reg 1 v ack $end
$var reg 8 w rdata [7:0] $end
$var reg 1 x vo $end
$scope module regr $end
$var wire 8 y a [7:0] $end
$var wire 1 a clk $end
$var wire 1 s en $end
$var wire 8 z q [7:0] $end
$var wire 1 f reset $end
$var reg 8 { q_i [7:0] $end
$upscope $end
$scope module f4 $end
$var wire 1 a clk $end
$var wire 1 e d $end
$var wire 1 p q $end
$var wire 1 f reset $end
$var reg 1 | q_i $end
$upscope $end
$scope module f5 $end
$var wire 1 a clk $end
$var wire 1 p d $end
$var wire 1 q q $end
$var wire 1 f reset $end
$var reg 1 } q_i $end
$upscope $end
$scope module f6 $end
$var wire 1 a clk $end
$var wire 1 q d $end
$var wire 1 r q $end
$var wire 1 f reset $end
$var reg 1 ~ q_i $end
$upscope $end
$scope module f7 $end
$var wire 1 a clk $end
$var wire 1 q d $end
$var wire 1 n q $end
$var wire 1 f reset $end
$var reg 1 !" q_i $end
$upscope $end
$scope module f8 $end
$var wire 1 a clk $end
$var wire 1 s d $end
$var wire 1 u q $end
$var wire 1 f reset $end
$var reg 1 "" q_i $end
$upscope $end
$scope module and3 $end
$var wire 1 q a $end
$var wire 1 #" b $end
$var wire 1 s q $end
$upscope $end
$upscope $end
$scope module tx $end
$var wire 1 $" a1 $end
$var wire 1 %" a2 $end
$var wire 1 &" a3 $end
$var wire 1 ` ack $end
$var wire 1 b clk $end
$var wire 8 '" data1 [7:0] $end
$var wire 1 (" req1 $end
$var wire 1 f reset $end
$var wire 8 )" sdata [7:0] $end
$var wire 1 *" snt1 $end
$var wire 1 +" txe $end
$var wire 1 i vi $end
$var reg 8 ," data [7:0] $end
$var reg 1 -" req $end
$var reg 1 ." snt $end
$scope module regt $end
$var wire 8 /" a [7:0] $end
$var wire 1 b clk $end
$var wire 1 +" en $end
$var wire 8 0" q [7:0] $end
$var wire 1 f reset $end
$var reg 8 1" q_i [7:0] $end
$upscope $end
$scope module txfsm $end
$var wire 1 %" a2 $end
$var wire 1 b clk $end
$var wire 1 f reset $end
$var wire 1 i vi $end
$var reg 2 2" current_state [1:0] $end
$var reg 2 3" next_state [1:0] $end
$var reg 1 4" req $end
$var reg 1 5" txe $end
$upscope $end
$scope module f1 $end
$var wire 1 b clk $end
$var wire 1 ` d $end
$var wire 1 $" q $end
$var wire 1 f reset $end
$var reg 1 6" q_i $end
$upscope $end
$scope module f2 $end
$var wire 1 b clk $end
$var wire 1 $" d $end
$var wire 1 %" q $end
$var wire 1 f reset $end
$var reg 1 7" q_i $end
$upscope $end
$scope module f3 $end
$var wire 1 b clk $end
$var wire 1 %" d $end
$var wire 1 &" q $end
$var wire 1 f reset $end
$var reg 1 8" q_i $end
$upscope $end
$scope module and1 $end
$var wire 1 9" a $end
$var wire 1 %" b $end
$var wire 1 *" q $end
$upscope $end
$upscope $end
$upscope $end
$upscope $end
$scope module tff $end
$var wire 1 :" clk $end
$var wire 1 ;" q $end
$var wire 1 <" qbar $end
$var wire 1 =" reset $end
$var wire 1 >" t $end
$var reg 1 ?" q_i $end
$upscope $end
$scope module xor2 $end
$var wire 1 @" a $end
$var wire 1 A" b $end
$var wire 1 B" q $end
$upscope $end
$scope module xor3 $end
$var wire 1 C" a $end
$var wire 1 D" b $end
$var wire 1 E" c $end
$var wire 1 F" q $end
$upscope $end
$enddefinitions $end
#0
$dumpvars
xF"
zE"
zD"
zC"
xB"
zA"
z@"
x?"
z>"
z="
x<"
x;"
z:"
x9"
x8"
x7"
x6"
x5"
x4"
bx 3"
bx 2"
bx 1"
bx 0"
bx /"
x."
x-"
bx ,"
x+"
x*"
bx )"
x("
bx '"
x&"
x%"
x$"
x#"
x""
x!"
x~
x}
x|
bx {
bx z
bx y
xx
bx w
xv
xu
bx t
xs
xr
xq
xp
bx o
xn
xm
xl
bx k
xj
xi
xh
bx g
xf
xe
bx d
bx c
0b
0a
x`
x_
x^
bx ]
bx \
0[
0Z
xY
xX
bx W
xV
xU
zT
zS
xR
xQ
xP
zO
xN
zM
zL
zK
zJ
bx I
zH
bx G
zF
zE
zD
bz C
bx B
zA
bx @
z?
bz >
x=
z<
z;
z:
z9
x8
z7
z6
z5
z4
bz 3
x2
z1
x0
z/
x.
x-
z,
z+
z*
z)
x(
z'
z&
z%
x$
z#
z"
z!
$end
#1
0-"
0e
b1 3"
05"
0+"
04"
0("
z4
0_
0i
1[
1a
1Z
1b
z*
#2
b1 3"
08"
07"
06"
b0 2"
b0 1"
0""
0!"
0~
0}
0|
b0 {
b1 ]
1^
1f
0[
0a
0Z
0b
#3
bx 1"
15"
1+"
x""
b1 2"
x6"
b0 k
b0 W
0m
0Y
19"
b1 3"
b0 ,"
b0 c
1#"
0x
0j
0v
0`
b0 w
b0 d
0&"
0%"
0$"
b0 '"
b0 0"
0u
0n
0r
0q
0p
b0 t
b0 z
0^
0f
1[
1a
1Z
1b
#4
xm
xY
0l
0X
xx
xj
0."
0h
bx ,"
bx c
bx '"
bx 0"
xu
x$"
0*"
0s
b11000111 \
b11000111 g
b11000111 o
b11000111 y
b11000111 )"
b11000111 /"
0[
0a
0Z
0b
#5
0""
x7"
06"
b11000111 1"
b10 3"
1_
1i
1[
1a
1Z
1b
#6
0m
0Y
0x
0j
b1 3"
b11000111 ,"
b11000111 c
0u
x%"
0$"
b11000111 '"
b11000111 0"
0[
0a
0Z
0b
#7
07"
x8"
xl
xX
x."
xh
x*"
1[
1a
1Z
1b
#8
b10 3"
x9"
0%"
x&"
0[
0a
0Z
0b
#9
1-"
1e
14"
1("
08"
b10 2"
0l
0X
0."
0h
0*"
1[
1a
1Z
1b
#10
19"
0&"
0[
0a
0Z
0b
0_
0i
#11
1|
1[
1a
1Z
1b
#12
1p
0[
0a
0Z
0b
#13
1}
1[
1a
1Z
1b
#14
1q
0[
0a
0Z
0b
#15
1~
1!"
1""
b11000111 {
1s
1[
1a
1Z
1b
#16
b11000111 k
b11000111 W
1m
1Y
0#"
1x
1j
1v
1`
b11000111 w
b11000111 d
1r
1n
1u
b11000111 t
b11000111 z
0[
0a
0Z
0b
#17
0""
16"
0s
1[
1a
1Z
1b
#18
0m
0Y
0x
0j
0u
1$"
0[
0a
0Z
0b
#19
17"
1[
1a
1Z
1b
#20
b1 3"
1%"
0[
0a
0Z
0b
#21
0-"
0e
04"
0("
18"
b1 2"
1l
1X
1."
1h
1*"
1[
1a
1Z
1b
#22
09"
1&"
0[
0a
0Z
0b
#23
0|
0l
0X
0."
0h
0*"
1[
1a
1Z
1b
#24
0p
0[
0a
0Z
0b
#25
0}
1[
1a
1Z
1b
#26
0q
0[
0a
0Z
0b
#27
0~
0!"
1[
1a
1Z
1b
#28
1#"
0v
0`
0r
0n
0[
0a
0Z
0b
#29
06"
1[
1a
1Z
1b
#30
0$"
0[
0a
0Z
0b
#31
07"
1[
1a
1Z
1b
#32
0%"
0[
0a
0Z
0b
#33
08"
1[
1a
1Z
1b
#34
19"
0&"
0[
0a
0Z
0b
